<?xml version="1.0" encoding="UTF-8"?>

<beans xmlns="http://www.springframework.org/schema/beans" xmlns:xsi="http://www.w3.org/2001/XMLSchema-instance"
	xmlns:mvc="http://www.springframework.org/schema/mvc" xmlns:context="http://www.springframework.org/schema/context"
	xsi:schemaLocation="http://www.springframework.org/schema/mvc http://www.springframework.org/schema/mvc/spring-mvc.xsd
		http://www.springframework.org/schema/beans http://www.springframework.org/schema/beans/spring-beans.xsd
		http://www.springframework.org/schema/context http://www.springframework.org/schema/context/spring-context.xsd">

 	<context:component-scan base-package="pack.controller" />
	<context:component-scan base-package="parkinglot.controller" />
	<context:component-scan base-package="member.controller" />
	<context:component-scan base-package="illegal.controller" />
	<context:component-scan base-package="serviceinfo.controller" />
    
    <mvc:annotation-driven />

	<bean class="org.springframework.web.servlet.view.InternalResourceViewResolver">
	        <!-- Example: a logical view name of 'showMessage' is mapped to '/WEB-INF/jsp/showMessage.jsp' -->
	        <property name="prefix" value="/WEB-INF/view/"/>
	        <property name="suffix" value=".jsp"/>
	</bean>

	<!-- bootstrap css/js mapping -->
	<mvc:resources location = "/bootstrap/" mapping = "/bootstrap/**" />

	<!-- css/js mapping -->
	<mvc:resources location= "/resources/" mapping= "/resources/**" />
	
	<!-- file upload -->
	<bean id="multipartResolver" 
		class="org.springframework.web.multipart.commons.CommonsMultipartResolver"/>
	<!-- file download -->
	<bean class="org.springframework.web.servlet.view.BeanNameViewResolver">
		<property name="order" value="0" />
	</bean>
	
	
	<!-- Mail Sender : 보내는 메일계정 지정 -->
	<bean id="mailSender" class="org.springframework.mail.javamail.JavaMailSenderImpl">
		<property name="host" value="smtp.gmail.com" />
		<property name="port" value="587" />
		<property name="username" value="park.acorn@gmail.com" />
		<property name="password" value="park12345" /> 
		<property name="javaMailProperties">
	            <props>
       	      		<prop key="mail.smtp.auth">true</prop> <!-- 마지막 주에서 추가됨 -->
	                <prop key="mail.smtp.starttls.enable">true</prop>     
	            </props>
		</property>
	</bean>
	
	
</beans>

	